pycoolmasternet_ng/__init__.py
pycoolmasternet_ng/constants.py
pycoolmasternet_ng/data.py
pycoolmasternet_ng/exceptions.py
pycoolmasternet_ng/models.py
pycoolmasternet_ng/structures.py
pycoolmasternet_ng/transports.py
pycoolmasternet_ng-0.3.2.dist-info/LICENSE
pycoolmasternet_ng-0.3.2.dist-info/METADATA
pycoolmasternet_ng-0.3.2.dist-info/WHEEL
pycoolmasternet_ng-0.3.2.dist-info/top_level.txt
pycoolmasternet_ng-0.3.2.dist-info/RECORD
