Metadata-Version: 2.1
Name: pycoolmasternet-ng
Version: 0.3.2
Summary: Python client for CoolAutomation HVAC gateways.
Home-page: https://github.com/Rjevski/pycoolmasternet-ng
Author: Andre Borie
Author-email: hi@rjevski.io
Project-URL: Bug Tracker, https://github.com/Rjevski/pycoolmasternet-ng/issues
Classifier: Programming Language :: Python :: 3
Classifier: License :: OSI Approved :: MIT License
Classifier: Operating System :: OS Independent
Classifier: Development Status :: 3 - Alpha
Classifier: Intended Audience :: Developers
Classifier: Programming Language :: Python
Classifier: Programming Language :: Python :: 3
Classifier: Programming Language :: Python :: 3.9
Classifier: Topic :: Home Automation
Classifier: Topic :: Scientific/Engineering :: Interface Engine/Protocol Translator
Classifier: Topic :: Software Development :: Libraries
Classifier: Topic :: System :: Hardware :: Hardware Drivers
Requires-Python: >=3.9
License-File: LICENSE
Provides-Extra: serial
Requires-Dist: pyserial-asyncio ; extra == 'serial'
